Metadata-Version: 2.1
Name: aiosocketpool
Version: 0.0.2
Summary: An asyncio-compatible socket pool
Home-page: https://github.com/polyatail/aiosocketpool
Author: Roo Sczesnak
Author-email: andrewscz@gmail.com
License: MIT License
Platform: UNKNOWN
Provides-Extra: testing
